README.txt
setup.py
bin/shrinkwrap
shrinkwrap/__init__.py
shrinkwrap/command.py
shrinkwrap/install.py
shrinkwrap.egg-info/PKG-INFO
shrinkwrap.egg-info/SOURCES.txt
shrinkwrap.egg-info/dependency_links.txt
shrinkwrap.egg-info/entry_points.txt
shrinkwrap.egg-info/top_level.txt