Metadata-Version: 1.0
Name: shrinkwrap
Version: 0.9
Summary: Helper modules for making wrapper packages around non-Python code.
Home-page: http://bitbucket.org/seibert/shrinkwrap/
Author: Stan Seibert
Author-email: stan@mtrr.org
License: LICENSE.txt
Platform: UNKNOWN
